asmlib/Assembler.py
asmlib/BitVec.py
asmlib/Error.py
asmlib/Lexing.py
asmlib/Parsing.py
asmlib/Riscv.py
asmlib/Simulation.py
asmlib/Toy.py
asmlib/Version.py
asmlib/__init__.py
asmlib/Tools/riscvasm.py
asmlib/Tools/riscvsim.py
asmlib/Tools/toyasm.py
asmlib/Tools/toysim.py
asmlib-2.2.0.dist-info/LICENSE
asmlib-2.2.0.dist-info/METADATA
asmlib-2.2.0.dist-info/WHEEL
asmlib-2.2.0.dist-info/entry_points.txt
asmlib-2.2.0.dist-info/top_level.txt
asmlib-2.2.0.dist-info/RECORD
