Metadata-Version: 2.1
Name: asmlib
Version: 2.2.0
Summary: Tooling package for the computer architecture course at Graz University of Technology.
Home-page: https://extgit.iaik.tugraz.at/con/asmlib
Author: Robert Schilling
Author-email: schilling.ro@gmail.com
License: GPLv3
Keywords: TOY assembler simulator computer architecture teaching
Platform: UNKNOWN
Classifier: Development Status :: 5 - Production/Stable
Classifier: Intended Audience :: Developers
Classifier: Intended Audience :: Science/Research
Classifier: License :: OSI Approved :: GNU General Public License v3 (GPLv3)
Classifier: Operating System :: OS Independent
Classifier: Programming Language :: Python :: 3.5
Classifier: Topic :: Scientific/Engineering
Classifier: Topic :: Software Development :: Build Tools
Classifier: Topic :: Utilities
Requires-Python: >=3.5
Provides-Extra: documentation
